potpourri3d_bindings.cpython-38-i386-linux-gnu.so
potpourri3d-1.3.dist-info/WHEEL
potpourri3d-1.3.dist-info/RECORD
potpourri3d-1.3.dist-info/METADATA
potpourri3d-1.3.dist-info/licenses/LICENSE
lib/libgeometry-central.a
potpourri3d/core.py
potpourri3d/mesh.py
potpourri3d/io.py
potpourri3d/__init__.py
potpourri3d/point_cloud.py
potpourri3d.libs/libgcc_s-f3fb5a36.so.1
potpourri3d.libs/libstdc++-d2a021ba.so.6.0.32
