Metadata-Version: 2.1
Name: potpourri3d
Version: 1.3
Summary: An invigorating blend of 3D geometry tools in Python.
Author-Email: Nicholas Sharp <nmwsharp@gmail.com>
Maintainer-Email: Nicholas Sharp <nmwsharp@gmail.com>
License: MIT License
Classifier: Development Status :: 5 - Production/Stable
Classifier: License :: OSI Approved :: MIT License
Classifier: Programming Language :: Python :: 3
Project-URL: Homepage, https://github.com/nmwsharp/potpourri3d
Requires-Python: >=3.7
Requires-Dist: numpy
Requires-Dist: scipy
